spoonacular/__init__.py
spoonacular/api.py
spoonacular/endpoint_quotas.py
spoonacular-3.0.dist-info/LICENSE
spoonacular-3.0.dist-info/METADATA
spoonacular-3.0.dist-info/WHEEL
spoonacular-3.0.dist-info/top_level.txt
spoonacular-3.0.dist-info/RECORD
