Metadata-Version: 2.1
Name: spoonacular
Version: 3.0
Summary: A Python wrapper for the Spoonacular API
Home-page: https://github.com/johnwmillr/SpoonacularAPI
Author: John W. Miller
License: MIT
Keywords: spoonacular API food recipes ingredients cuisine groceries
Platform: UNKNOWN
Classifier: Topic :: Software Development :: Libraries
Classifier: Operating System :: OS Independent
Classifier: Programming Language :: Python
Classifier: Programming Language :: Python :: 3
Requires-Python: >=3.*
